runai_interactive_context/__about__.py
runai_interactive_context/__init__.py
runai_interactive_context/__main__.py
runai_interactive_context/cli.py
runai_interactive_context-0.0.2.dist-info/METADATA
runai_interactive_context-0.0.2.dist-info/WHEEL
runai_interactive_context-0.0.2.dist-info/entry_points.txt
runai_interactive_context-0.0.2.dist-info/licenses/LICENSE.txt
runai_interactive_context-0.0.2.dist-info/RECORD
