Metadata-Version: 2.1
Name: runai-interactive-context
Version: 0.0.2
Summary: CLI to run an interactive session on RunAI with cleaning on exit to limit costs
Project-URL: Documentation, https://github.com/LSIR/runai-interactive-context#readme
Project-URL: Issues, https://github.com/LSIR/runai-interactive-context/issues
Project-URL: Source, https://github.com/LSIR/runai-interactive-context
Author-email: Stephane Massonnet <stephane.massonnet@epfl.ch>
License-Expression: MIT
License-File: LICENSE.txt
Classifier: Development Status :: 4 - Beta
Classifier: Programming Language :: Python
Classifier: Programming Language :: Python :: 3.9
Classifier: Programming Language :: Python :: 3.10
Classifier: Programming Language :: Python :: 3.11
Classifier: Programming Language :: Python :: Implementation :: CPython
Classifier: Programming Language :: Python :: Implementation :: PyPy
Requires-Python: >=3.9
Requires-Dist: retry
Requires-Dist: typer[all]
